Metadata-Version: 1.0
Name: roboticia-move
Version: 0.0.1
Summary: Roboticia-move Software Library
Home-page: https://github.com/Roboticia/Roboticia-move
Author: Julien JEHL
Author-email: julien.jehl@roboticia.com
License: GNU GENERAL PUBLIC LICENSE Version 3
Platform: UNKNOWN
